[
 {
  "anilistId": 105333,
  "slug": "dr-stone",
  "titleEnglish": "Dr. STONE",
  "titleRomaji": "Dr. STONE",
  "format": "TV",
  "status": "FINISHED",
  "episodes": 24,
  "episodeDuration": 24,
  "studio": "TMS Entertainment",
  "year": 2019,
  "averageScore": 81,
  "popularity": 532365,
  "coverImage": "https://s4.anilist.co/file/anilistcdn/media/anime/cover/medium/bx105333-GybuoSoOZfpH.jpg",
  "genres": [
   "Action",
   "Sci-Fi",
   "Adventure",
   "Comedy"
  ],
  "season": "SUMMER",
  "seasonYear": 2019
 },
 {
  "anilistId": 101348,
  "slug": "vinland-saga",
  "titleEnglish": "Vinland Saga",
  "titleRomaji": "VINLAND SAGA",
  "format": "TV",
  "status": "FINISHED",
  "episodes": 24,
  "episodeDuration": 24,
  "studio": "WIT STUDIO",
  "year": 2019,
  "averageScore": 87,
  "popularity": 517682,
  "coverImage": "https://s4.anilist.co/file/anilistcdn/media/anime/cover/medium/bx101348-2fhDFPCuMNiz.jpg",
  "genres": [
   "Action",
   "Adventure",
   "Drama"
  ],
  "season": "SUMMER",
  "seasonYear": 2019
 },
 {
  "anilistId": 105310,
  "slug": "fire-force",
  "titleEnglish": "Fire Force",
  "titleRomaji": "Enen no Shouboutai",
  "format": "TV",
  "status": "FINISHED",
  "episodes": 24,
  "episodeDuration": 24,
  "studio": "david production",
  "year": 2019,
  "averageScore": 76,
  "popularity": 463965,
  "coverImage": "https://s4.anilist.co/file/anilistcdn/media/anime/cover/medium/bx105310-2PKUvoaA6fTn.jpg",
  "genres": [
   "Action",
   "Sci-Fi",
   "Drama",
   "Supernatural"
  ],
  "season": "SUMMER",
  "seasonYear": 2019
 },
 {
  "anilistId": 106286,
  "slug": "weathering-with-you",
  "titleEnglish": "Weathering With You",
  "titleRomaji": "Tenki no Ko",
  "format": "MOVIE",
  "status": "FINISHED",
  "episodes": 1,
  "episodeDuration": 115,
  "studio": "CoMix Wave",
  "year": 2019,
  "averageScore": 81,
  "popularity": 341412,
  "coverImage": "https://s4.anilist.co/file/anilistcdn/media/anime/cover/medium/bx106286-5COcpd0J9VbL.png",
  "genres": [
   "Drama",
   "Slice of Life",
   "Romance",
   "Supernatural"
  ],
  "season": "SUMMER",
  "seasonYear": 2019
 }
]